hello_world/__init__.py
hello_world/disp.py
hello_world_lib-0.1.0.dist-info/METADATA
hello_world_lib-0.1.0.dist-info/WHEEL
hello_world_lib-0.1.0.dist-info/top_level.txt
hello_world_lib-0.1.0.dist-info/RECORD
