Metadata-Version: 2.1
Name: hello-world-lib
Version: 0.1.0
Summary: A simple library to display "Hello, World!"
Home-page: https://github.com/MissCoco01/testhello
Author: Ema
Author-email: 
